LinkedList/__init__.py
LinkedList/base_list.py
LinkedList/linked_list.py
LinkedList/linked_list_iterator.py
LinkedList/node.py
LinkedList_575-1.0.2.dist-info/LICENSE
LinkedList_575-1.0.2.dist-info/METADATA
LinkedList_575-1.0.2.dist-info/WHEEL
LinkedList_575-1.0.2.dist-info/top_level.txt
LinkedList_575-1.0.2.dist-info/RECORD
