Metadata-Version: 2.1
Name: LinkedList-575
Version: 1.0.2
Summary: A Python package for LinkedList data structure.
Home-page: https://github.com/Saqibs575/LinkedList
Author: Saqib Shaikh
Author-email: saquibs575@gmail.com
License: GNU General Public License v3.0
Project-URL: Source, https://github.com/Saqibs575/LinkedList
Project-URL: Bug Reports, https://github.com/Saqibs575/LinkedList/issues
Keywords: LinkedList,linkedlist,linked list,linkedlist in python ,linked list data-structure python package
Platform: win32
Platform: win-amd64
Platform: win-arm32
Platform: win-arm64
Platform: linux-x86
Platform: linux-x86_64
Platform: linux-armv6l
Platform: linux-armv7l
Platform: linux-aarch64
Platform: darwin
Platform: darwin-arm64
Platform: any
Classifier: License :: OSI Approved :: GNU General Public License v3 or later (GPLv3+)
Classifier: Programming Language :: Python :: 3
Classifier: Programming Language :: Python :: 3.6
Classifier: Programming Language :: Python :: 3.7
Classifier: Programming Language :: Python :: 3.8
Classifier: Programming Language :: Python :: 3.9
Classifier: Programming Language :: Python :: 3.10
Classifier: Programming Language :: Python :: 3.11
Classifier: Programming Language :: Python :: 3.12
Classifier: Operating System :: OS Independent
Requires-Python: >=3.6
License-File: LICENSE
